epics/__init__.py
epics/alarm.py
epics/ca.py
epics/dbr.py
epics/device.py
epics/motor.py
epics/multiproc.py
epics/pv.py
epics/utils.py
epics/version.py
epics/autosave/__init__.py
epics/autosave/save_restore.py
epics/clibs/__init__.py
epics/clibs/darwin64/README
epics/clibs/darwin64/libComPYEPICS.dylib
epics/clibs/darwin64/libca.dylib
epics/clibs/darwinarm64/README
epics/clibs/darwinarm64/libComPYEPICS.dylib
epics/clibs/darwinarm64/libca.dylib
epics/clibs/linux32/README
epics/clibs/linux32/libComPYEPICS.so
epics/clibs/linux32/libca.so
epics/clibs/linux64/README
epics/clibs/linux64/libComPYEPICS.so
epics/clibs/linux64/libca.so
epics/clibs/linuxarm/README
epics/clibs/linuxarm/libComPYEPICS.so
epics/clibs/linuxarm/libca.so
epics/clibs/win32/Com.dll
epics/clibs/win32/README
epics/clibs/win32/ca.dll
epics/clibs/win32/caRepeater.exe
epics/clibs/win64/Com.dll
epics/clibs/win64/README
epics/clibs/win64/ca.dll
epics/clibs/win64/caRepeater.exe
epics/compat/CaChannel.py
epics/compat/__init__.py
epics/compat/ca_util.py
epics/compat/epicsPV.py
epics/devices/__init__.py
epics/devices/ad_base.py
epics/devices/ad_fileplugin.py
epics/devices/ad_image.py
epics/devices/ad_mca.py
epics/devices/ad_overlay.py
epics/devices/ad_perkinelmer.py
epics/devices/ai.py
epics/devices/ao.py
epics/devices/bi.py
epics/devices/bo.py
epics/devices/mca.py
epics/devices/scaler.py
epics/devices/scan.py
epics/devices/srs570.py
epics/devices/struck.py
epics/devices/transform.py
epics/devices/xspress3.py
epics/qt/README
epics/qt/pvprobe_qt.py
epics/wx/__init__.py
epics/wx/motordetailframe.py
epics/wx/motorpanel.py
epics/wx/ogllib.py
epics/wx/utils.py
epics/wx/wxlib.py
epics/wx/wxutils.py
pyepics-3.5.9.dist-info/licenses/LICENSE
pyepics-3.5.9.dist-info/METADATA
pyepics-3.5.9.dist-info/WHEEL
pyepics-3.5.9.dist-info/top_level.txt
pyepics-3.5.9.dist-info/RECORD
