Metadata-Version: 2.4
Name: pyepics
Version: 3.5.9
Summary: Epics Channel Access for Python
Author-email: Matthew Newville <newville@cars.uchicago.edu>
Project-URL: Homepage, https://github.com/pyepics/pyepics/
Project-URL: Documentation, https://pyepics.github.io/pyepics/
Keywords: epics
Classifier: Development Status :: 5 - Production/Stable
Classifier: Intended Audience :: Science/Research
Classifier: Topic :: Scientific/Engineering
Classifier: Operating System :: OS Independent
Classifier: Programming Language :: Python :: 3
Classifier: Programming Language :: Python :: 3 :: Only
Classifier: Programming Language :: Python :: 3.10
Classifier: Programming Language :: Python :: 3.11
Classifier: Programming Language :: Python :: 3.12
Classifier: Programming Language :: Python :: 3.13
Classifier: Programming Language :: Python :: 3.14
Classifier: Programming Language :: Python :: Implementation :: CPython
Requires-Python: >=3.10
License-File: LICENSE
Requires-Dist: numpy>=1.26
Requires-Dist: pyparsing
Provides-Extra: doc
Requires-Dist: Sphinx; extra == "doc"
Requires-Dist: numpydoc; extra == "doc"
Provides-Extra: test
Requires-Dist: coverage; extra == "test"
Requires-Dist: pytest; extra == "test"
Requires-Dist: pytest-cov; extra == "test"
Requires-Dist: psutil; platform_system == "Linux" and extra == "test"
Provides-Extra: all
Requires-Dist: pyepics[doc,test]; extra == "all"
Dynamic: license-file
